conductor/__init__.py
conductor/client/__init__.py
conductor/client/ai/__init__.py
conductor/client/ai/configuration.py
conductor/client/ai/integrations.py
conductor/client/ai/orchestrator.py
conductor/client/authorization_client.py
conductor/client/automator/__init__.py
conductor/client/automator/async_task_runner.py
conductor/client/automator/json_schema_generator.py
conductor/client/automator/task_handler.py
conductor/client/automator/task_runner.py
conductor/client/automator/utils.py
conductor/client/configuration/__init__.py
conductor/client/configuration/configuration.py
conductor/client/configuration/settings/__init__.py
conductor/client/configuration/settings/authentication_settings.py
conductor/client/configuration/settings/metrics_settings.py
conductor/client/context/__init__.py
conductor/client/context/task_context.py
conductor/client/event/__init__.py
conductor/client/event/conductor_event.py
conductor/client/event/event_client.py
conductor/client/event/event_dispatcher.py
conductor/client/event/listener_register.py
conductor/client/event/listeners.py
conductor/client/event/queue/__init__.py
conductor/client/event/queue/kafka_queue_configuration.py
conductor/client/event/queue/queue_configuration.py
conductor/client/event/queue/queue_worker_configuration.py
conductor/client/event/sync_event_dispatcher.py
conductor/client/event/sync_listener_register.py
conductor/client/event/task_events.py
conductor/client/event/task_runner_events.py
conductor/client/event/workflow_events.py
conductor/client/exceptions/__init__.py
conductor/client/exceptions/api_error.py
conductor/client/exceptions/api_exception_handler.py
conductor/client/helpers/__init__.py
conductor/client/helpers/helper.py
conductor/client/http/__init__.py
conductor/client/http/api/__init__.py
conductor/client/http/api/application_resource_api.py
conductor/client/http/api/async_task_resource_api.py
conductor/client/http/api/authorization_resource_api.py
conductor_python-1.3.1.dist-info/METADATA
conductor_python-1.3.1.dist-info/WHEEL
conductor_python-1.3.1.dist-info/RECORD
