Metadata-Version: 2.4
Name: conductor-python
Version: 1.3.1
Summary: Python SDK for working with https://github.com/conductor-oss/conductor
License: Apache-2.0
Author: Orkes
Author-email: developers@orkes.io
Requires-Python: >=3.9,<3.13
Classifier: Development Status :: 5 - Production/Stable
Classifier: Intended Audience :: Developers
Classifier: Intended Audience :: System Administrators
Classifier: License :: OSI Approved :: Apache Software License
Classifier: Programming Language :: Python :: 3
Classifier: Programming Language :: Python :: 3.9
Classifier: Programming Language :: Python :: 3.10
Classifier: Programming Language :: Python :: 3.11
Classifier: Programming Language :: Python :: 3.12
Classifier: Topic :: Software Development :: Libraries :: Application Frameworks
Classifier: Topic :: Software Development :: Libraries :: Python Modules
Requires-Dist: astor (>=0.8.1)
Requires-Dist: certifi (>=14.05.14)
Requires-Dist: dacite (>=1.8.1)
Requires-Dist: deprecated (>=1.2.14)
Requires-Dist: h2 (>=4.1.0)
Requires-Dist: httpx[http2] (>=0.26.0)
Requires-Dist: prometheus-client (>=0.13.1)
Requires-Dist: python-dateutil (>=2.8.2,<3.0.0)
Requires-Dist: requests (>=2.31.0)
Requires-Dist: shortuuid (>=1.0.11)
Requires-Dist: six (>=1.10)
Requires-Dist: typing-extensions (>=4.2.0)
